{
    "collaborators": [
        "rncasagr"
    ],
    "created_at": "2018-10-16 23:05:01",
    "edges": [
        {
            "ports": [
                {
                    "output": "barDay",
                    "type": "png"
                }
            ],
            "source": "clean.R",
            "target": "barDay.png"
        },
        {
            "ports": [
                {
                    "input": "raw_data",
                    "type": "csv"
                }
            ],
            "source": "satisfactionSurvey.csv",
            "target": "summarize.R"
        }
    ],
    "nodes": [
        {
            "name": "satisfactionSurvey.csv"
        },
        {
            "assigned_to": "rncasagr",
            "name": "clean.R",
            "task_status": "in progress"
        },
        {
            "name": "barDay.png"
        },
        {
            "assigned_to": "rncasagr",
            "desc": "",
            "name": "summarize.R",
            "task_status": "in progress"
        },
        {
            "name": "summarizeDay.png"
        },
        {
            "name": "summarize.csv"
        }
    ],
    "updated_at": "2018-10-16 23:50:18",
    "url": "https://github.com/fall2018-saltz/rnl_project"
}